{
  "auth": {
    "user_pool_id": "us-west-2_ByTBOYUDh",
    "aws_region": "us-west-2",
    "user_pool_client_id": "3fhjbgv8q074r67hpfetutgvv",
    "identity_pool_id": "us-west-2:96d3eeff-e425-423a-9735-f7eca0fbc07c",
    "mfa_methods": [],
    "standard_required_attributes": [
      "email"
    ],
    "username_attributes": [
      "email"
    ],
    "user_verification_types": [
      "email"
    ],
    "groups": [],
    "mfa_configuration": "NONE",
    "password_policy": {
      "min_length": 8,
      "require_lowercase": true,
      "require_numbers": true,
      "require_symbols": true,
      "require_uppercase": true
    },
    "unauthenticated_identities_enabled": true
  },
  "data": {
    "url": "https://4vf5q2rr7bdjlmwuof2cfg7z4m.appsync-api.us-west-2.amazonaws.com/graphql",
    "aws_region": "us-west-2",
    "default_authorization_type": "AWS_IAM",
    "authorization_types": [
      "AMAZON_COGNITO_USER_POOLS"
    ],
    "model_introspection": {
      "version": 1,
      "models": {
        "Document": {
          "name": "Document",
          "fields": {
            "id": {
              "name": "id",
              "isArray": false,
              "type": "ID",
              "isRequired": true,
              "attributes": []
            },
            "filename": {
              "name": "filename",
              "isArray": false,
              "type": "String",
              "isRequired": false,
              "attributes": []
            },
            "path": {
              "name": "path",
              "isArray": false,
              "type": "String",
              "isRequired": false,
              "attributes": []
            },
            "topic": {
              "name": "topic",
              "isArray": false,
              "type": "String",
              "isRequired": false,
              "attributes": []
            },
            "text": {
              "name": "text",
              "isArray": false,
              "type": "String",
              "isRequired": false,
              "attributes": []
            },
            "embedding": {
              "name": "embedding",
              "isArray": false,
              "type": "String",
              "isRequired": false,
              "attributes": []
            },
            "embedding_provider": {
              "name": "embedding_provider",
              "isArray": false,
              "type": "String",
              "isRequired": false,
              "attributes": []
            },
            "createdAt": {
              "name": "createdAt",
              "isArray": false,
              "type": "AWSDateTime",
              "isRequired": false,
              "attributes": [],
              "isReadOnly": true
            },
            "updatedAt": {
              "name": "updatedAt",
              "isArray": false,
              "type": "AWSDateTime",
              "isRequired": false,
              "attributes": [],
              "isReadOnly": true
            }
          },
          "syncable": true,
          "pluralName": "Documents",
          "attributes": [
            {
              "type": "model",
              "properties": {}
            },
            {
              "type": "auth",
              "properties": {
                "rules": [
                  {
                    "groupClaim": "cognito:groups",
                    "provider": "userPools",
                    "allow": "groups",
                    "groups": [
                      "admin"
                    ],
                    "operations": [
                      "create",
                      "update",
                      "delete",
                      "read"
                    ]
                  }
                ]
              }
            }
          ],
          "primaryKeyInfo": {
            "isCustomPrimaryKey": false,
            "primaryKeyFieldName": "id",
            "sortKeyFieldNames": []
          }
        }
      },
      "enums": {},
      "nonModels": {
        "ChatResponse": {
          "name": "ChatResponse",
          "fields": {
            "reply": {
              "name": "reply",
              "isArray": false,
              "type": "String",
              "isRequired": false,
              "attributes": []
            },
            "error": {
              "name": "error",
              "isArray": false,
              "type": "String",
              "isRequired": false,
              "attributes": []
            }
          }
        },
        "TopicList": {
          "name": "TopicList",
          "fields": {
            "topics": {
              "name": "topics",
              "isArray": true,
              "type": "String",
              "isRequired": false,
              "attributes": [],
              "isArrayNullable": true
            }
          }
        },
        "OperationStatus": {
          "name": "OperationStatus",
          "fields": {
            "ok": {
              "name": "ok",
              "isArray": false,
              "type": "Boolean",
              "isRequired": false,
              "attributes": []
            },
            "message": {
              "name": "message",
              "isArray": false,
              "type": "String",
              "isRequired": false,
              "attributes": []
            },
            "total": {
              "name": "total",
              "isArray": false,
              "type": "Int",
              "isRequired": false,
              "attributes": []
            }
          }
        }
      },
      "queries": {
        "documentsTopics": {
          "name": "documentsTopics",
          "isArray": false,
          "type": {
            "nonModel": "TopicList"
          },
          "isRequired": false
        }
      },
      "mutations": {
        "chat": {
          "name": "chat",
          "isArray": false,
          "type": {
            "nonModel": "ChatResponse"
          },
          "isRequired": false,
          "arguments": {
            "messagesJson": {
              "name": "messagesJson",
              "isArray": false,
              "type": "String",
              "isRequired": true
            },
            "provider": {
              "name": "provider",
              "isArray": false,
              "type": "String",
              "isRequired": false
            },
            "topic": {
              "name": "topic",
              "isArray": false,
              "type": "String",
              "isRequired": false
            }
          }
        },
        "documentsImportTopic": {
          "name": "documentsImportTopic",
          "isArray": false,
          "type": {
            "nonModel": "OperationStatus"
          },
          "isRequired": false,
          "arguments": {
            "topic": {
              "name": "topic",
              "isArray": false,
              "type": "String",
              "isRequired": true
            },
            "provider": {
              "name": "provider",
              "isArray": false,
              "type": "String",
              "isRequired": false
            }
          }
        },
        "documentsPreprocess": {
          "name": "documentsPreprocess",
          "isArray": false,
          "type": {
            "nonModel": "OperationStatus"
          },
          "isRequired": false,
          "arguments": {
            "provider": {
              "name": "provider",
              "isArray": false,
              "type": "String",
              "isRequired": false
            }
          }
        }
      }
    }
  },
  "version": "1.4"
}